jax_resnet/__init__.py
jax_resnet/common.py
jax_resnet/pretrained.py
jax_resnet/resnet.py
jax_resnet/splat.py
jax_resnet-0.0.4.dist-info/LICENSE
jax_resnet-0.0.4.dist-info/METADATA
jax_resnet-0.0.4.dist-info/WHEEL
jax_resnet-0.0.4.dist-info/top_level.txt
jax_resnet-0.0.4.dist-info/zip-safe
jax_resnet-0.0.4.dist-info/RECORD
