Metadata-Version: 2.1
Name: jax-resnet
Version: 0.0.4
Summary: Framework-agnostic library for checking array shapes at runtime.
Home-page: https://github.com/n2cholas/jax-resnet
Author: Nicholas Vadivelu
Author-email: nicholas.vadivelu@gmail.com
License: MIT
Platform: UNKNOWN
License-File: LICENSE
Requires-Dist: jax
Requires-Dist: jaxlib
Requires-Dist: flax
